{
  "event_uid": "foxl-cfjha-ev",
  "event_official_name": "Fox Lea Farm CFJHA",
  "aliases": "",
  "event_official_url": "https://www.foxleafarm.net/events",
  "start_date": "2025-11-06",
  "end_date": "2025-11-09",
  "event_days_till": "20 days",
  "event_month": "November",
  "event_short_description": "",
  "event_description": "",
  "event_season": "Fall",
  "event_duration": "4 days",
  "event-state": "Starts in 20 days",
  "ratings": "",
  "legs": "0",
  "event_link": "https://items.clearroundtravel.com/items/events/foxl-cfjha-ev.json",
  "venue_link": "https://items.clearroundtravel.com/items/venues/foxl-venue.json"
}
