{
  "event_uid": "wef-summer-ev",
  "event_official_link": "",
  "event_official_name": "ESP Summer Series",
  "event_display_name": "ESP Summer Series",
  "start_date": "2025-08-14",
  "end_date": "2025-08-24",
  "yyyymm": "",
  "event_month": "August",
  "today": "9/26/2025",
  "event_days_till": "-44 days",
  "event_estimated_next_start_date": "",
  "venue_uid": "wef-venue",
  "event_season": "Summer",
  "event_duration": "11 days",
  "event-current-status": "Complete (next in approx NaN days)",
  "event_recordId": "rec6Aystrm0sTxQgL",
  "events_backlog": "",
  "event-state": "Complete",
  "source_uids": [],
  "organizer_uid": "wec-org",
  "annual": "",
  "month_uid": "aug",
  "year_uid": "2025",
  "season_uid": "summer",
  "event_year": "2025",
  "response": "",
  "dir_uid": "",
  "country_uid": "united-states",
  "public_leg_label": "",
  "proxy": "https://crt-b1434e13de34.herokuapp.com/items",
  "update_rows": "",
  "commit_uri": "https://crt-b1434e13de34.herokuapp.com/items/commit",
  "platforms": "",
  "hub_uid": "wef-summer_hb",
  "legs": "0",
  "leg_uids": [],
  "legs_rollup": "0",
  "venue_uid (from hub_uid)": "wef-venue",
  "hub_end (from hub_uid)": "2025-08-24",
  "hub_start (from hub_uid)": "2025-08-14",
  "state_uid (from venue_uid)": "fl",
  "venue_official_link (from venue_uid)": "https://wellingtoninternational.com/",
  "venue_geo_lat (from venue_uid)": "26.6335313",
  "venue_geo_lon (from venue_uid)": "-80.27086079999999",
  "venue_zip (from venue_uid)": "33414",
  "city_uid (from venue_uid)": "wellington",
  "city_uid": "wellington",
  "state_uid": "fl",
  "organizer_uids (from venue_uid)": "wef-org",
  "event_season_hh": "summer",
  "hub-name_display (from hub_uid)": "",
  "hub_name_der (from hub_uid)": "ESP Summer",
  "hub-leg-label (from hub_uid)": "",
  "last_modified": "9/27/2025 4:54pm",
  "created": "9/22/2025",
  "event_month_mmm": "Aug",
  "event_link": "",
  "data-locale-link": "",
  "data-locale-resp": "",
  "rating_uids": [],
  "event_overview": "",
  "before_you_go": "",
  "entries_and_splits": "",
  "special_highlights": "",
  "logistics_highlights": "",
  "key_deadlines": "",
  "on_site_services": "",
  "parking_and_access": "",
  "watch_list": "",
  "owner_cta": "",
  "seo_keywords_csv": "",
  "rating_uids_csv": "",
  "insider_jargon_csv": "",
  "hub_name_helper": "",
  "event_json": "wef-summer-ev.json",
  "table_name": "events/"
}
