{
  "show_uid": "september-national",
  "created_date": "2025-08-27",
  "last_updated": "2025-08-27",
  "meta": {
    "official_link": "https://www.horseshowsonline.com/ShowDetails?ShowGUID=695e9ffa-e808-45d2-8796-57fea69b29d1",
    "official_name": "SEPTEMBER NATIONAL",
    "display_name": "September National",
    "official_start_date": "2025-09-04",
    "official_end_date": "2025-09-07",
    "venue_name": "fox-lea-farm",
    "venue_city": "venice",
    "flags": {
      "is_championship": false,
      "championship_type": null,
      "is_annual": true,
      "is_series": false,
      "series_label": null,
      "series_week": null
    },
    "ratings": {
      "usef_hunter_rating": {
        "code": "A",
        "label": "National"
      },
      "fei": {
        "code": null,
        "discipline": null,
        "stars": null,
        "category": null
      }
    },
    "notes": "Organizer page lists 'Fox Lea September 4-7'; entry portal lists 'SEPTEMBER NATIONAL' with USEF rating A (#4030). Using entry portal title as official_name; venue inferred as Fox Lea Farm, Venice.",
    "sources": [
      {
        "source_name": "horseshowsonline-com",
        "source_link": "https://www.horseshowsonline.com/ShowDetails?ShowGUID=695e9ffa-e808-45d2-8796-57fea69b29d1"
      },
      {
        "source_name": "foxleafarm-net",
        "source_link": "https://www.foxleafarm.net/fall-rated-h-j-shows"
      }
    ]
  },
  "derived": {
    "start_date": "2025-09-04",
    "yyyymm": "202509",
    "month_name": "September",
    "season": "fall",
    "status_window": "upcoming"
  },
  "suggested_save_path": "/shows/annual/september-national.json"
}
