{
  "geometry_uid": "gde-geometry",
  "venue_name": "Galway Downs Main Entrance",
  "place_id": "ChIJV8nZM3mC24ARHT1oxeSA55M",
  "geometry_link": "https://items.clearroundtravel.com/items/geometry/gde-geometry.json",
  "vacinity": "38801 Los Corralitos Rd, Temecula",
  "lng": "-117.0367934",
  "lat": "33.4854381",
  "city": "Temecula",
  "state": "CA",
  "types_comma": "point_of_interest, establishment",
  "created": "2025-10-20",
  "last_modified": "2025-10-23 9:12am",
  "seasonal_normal_winter": "",
  "seasonal_normal_spring": "",
  "seasonal_normal_summer": "",
  "seasonal_normal_fall": "",
  "geometry_record_id": "rec7Q0tZ6pIDKjkJc",
  "venue_link": "https://items.clearroundtravel.com/items/venues/gde-venue.json"
}
