{
  "spot_preview_uid": "enterprise-car-hll",
  "formatted_address": "207 E Main St, St. Charles, IL 60174",
  "official_link": "https://www.enterprise.com",
  "notes": "Local branch with SUVs and vans for barn teams.",
  "essential_grocery_uid": "",
  "on-site-check": "",
  "name": "Enterprise Rent-A-Car",
  "hours_text": "",
  "service_uids": [
    "car-rental",
    "suvs",
    "one-way-drop"
  ],
  "type": "car",
  "spot_helper": "Enterprise car hll",
  "safety_notes": "Central St. Charles office, safe and well lit.",
  "normalized_name": "Enterprise",
  "venue_uid": "hll-venue",
  "locality": "Rent",
  "spots_json": "enterprise-car-hll.json",
  "table_name": "spots/",
  "essential_uuid": "hll-essentials",
  "type_uid": "car",
  "dirs": "spots",
  "essential_cart_uid": "",
  "essential_feed_uid": "",
  "essential_pharmacy_uid": "",
  "essential_car_uid": "hll-essentials",
  "full_path": "https://crt-b1434e13de34.herokuapp.com/items/spots/enterprise-car-hll.json",
  "search_param": "enterprise+car"
}
